README.txt
setup.py
docs/HISTORY.txt
docs/INSTALL.txt
dv/__init__.py
dv.xdvserver.egg-info/PKG-INFO
dv.xdvserver.egg-info/SOURCES.txt
dv.xdvserver.egg-info/dependency_links.txt
dv.xdvserver.egg-info/entry_points.txt
dv.xdvserver.egg-info/namespace_packages.txt
dv.xdvserver.egg-info/not-zip-safe
dv.xdvserver.egg-info/requires.txt
dv.xdvserver.egg-info/top_level.txt
dv/xdvserver/__init__.py
dv/xdvserver/filter.py