Metadata-Version: 1.0
Name: dv.xdvserver
Version: 1.0b7
Summary: A server for the Deliverance/XSLT compiler
Home-page: http://open-plans.org/projects/deliverance
Author: Martin Aspeli
Author-email: optilude@gmail.com
License: BSD
Keywords: Deliverance XSLT WSGI
Platform: UNKNOWN
Classifier: Framework :: Plone
Classifier: Programming Language :: Python
Classifier: Topic :: Software Development :: Libraries :: Python Modules
